{"lang": "en", "retweeted_status": {"lang": "en", "text": "Don\u2019t wait. Register today.\n800-621-FEMA (3362) or http://t.co/03xvfBLf4h\n#COflood", "created_at": "Sat Nov 09 18:25:44 +0000 2013", "hashtags": [{"text": "COflood"}], "user_mentions": [], "source": "<a href=\"http://www.hootsuite.com\" rel=\"nofollow\">Hootsuite</a>", "user": {"id": 18487428}, "urls": [{"url": "http://t.co/03xvfBLf4h", "expanded_url": "http://DisasterAssistance.gov"}], "retweet_count": 3, "id": 399241411595612160, "id_str": "399241411595612160"}, "deleted": false, "text": "RT @femaregion8: Don\u2019t wait. Register today.\n800-621-FEMA (3362) or http://t.co/03xvfBLf4h\n#COflood", "created_at": "Sat Nov 09 21:09:34 +0000 2013", "hashtags": [{"text": "COflood"}], "user_mentions": [{"id": 18487428, "screen_name": "femaregion8", "name": "FEMA Region 8"}], "source": "<a href=\"http://blackberry.com/twitter\" rel=\"nofollow\">Twitter for BlackBerry\u00ae</a>", "user": {"id": 235217558}, "urls": [{"url": "http://t.co/03xvfBLf4h", "expanded_url": "http://DisasterAssistance.gov"}], "retrieved": "2018-01-21--05-57-20", "retweet_count": 3, "id": 399282640160714752, "id_str": "399282640160714752"}