{"lang": "en", "deleted": false, "text": "via @USATODAY \"Federal exchange sends unqualified people to Medicaid\" http://t.co/FIQp1jYHzq", "created_at": "Mon Dec 09 19:16:41 +0000 2013", "hashtags": [], "user_mentions": [{"id": 15754281, "screen_name": "USATODAY", "name": "USA TODAY"}], "source": "<a href=\"http://twitter.com\" rel=\"nofollow\">Twitter Web Client</a>", "user": {"id": 235217558}, "urls": [{"url": "http://t.co/FIQp1jYHzq", "expanded_url": "http://usat.ly/IKYMnj"}], "retrieved": "2018-01-21--05-57-20", "retweet_count": 2, "id": 410125868095123456, "id_str": "410125868095123456"}