{"lang": "en", "retweeted_status": {"lang": "en", "text": "\"No more false promises, no more political games. It's time for transparency &amp; truth\" --Chairman @RepFredUpton #AskSebelius", "created_at": "Wed Dec 11 15:58:14 +0000 2013", "hashtags": [{"text": "AskSebelius"}], "user_mentions": [{"id": 124224165, "screen_name": "RepFredUpton", "name": "Fred Upton"}], "source": "<a href=\"http://twitter.com\" rel=\"nofollow\">Twitter Web Client</a>", "user": {"id": 114756202}, "urls": [], "retweet_count": 5, "id": 410800701950791680, "favorite_count": 1, "id_str": "410800701950791680"}, "deleted": false, "text": "RT @HouseCommerce: \"No more false promises, no more political games. It's time for transparency &amp; truth\" --Chairman @RepFredUpton #AskSebel\u2026", "created_at": "Wed Dec 11 16:10:49 +0000 2013", "hashtags": [], "user_mentions": [{"id": 114756202, "screen_name": "HouseCommerce", "name": "Energy and Commerce"}, {"id": 124224165, "screen_name": "RepFredUpton", "name": "Fred Upton"}], "source": "<a href=\"http://twitter.com\" rel=\"nofollow\">Twitter Web Client</a>", "user": {"id": 235217558}, "urls": [], "retrieved": "2018-01-21--05-57-20", "retweet_count": 5, "id": 410803869959331841, "id_str": "410803869959331841"}