{"lang": "en", "deleted": false, "text": "Members of Congress should not play games with the lives of the people they serve. The livelihood and well-being... http://fb.me/1bwGsBNKP", "created_at": "Fri Aug 05 13:50:17 +0000 2011", "hashtags": [], "user_mentions": [], "source": "<a href=\"http://www.facebook.com/twitter\" rel=\"nofollow\">Facebook</a>", "user": {"id": 29450962}, "urls": [], "retrieved": "2018-01-27--02-31-02", "retweet_count": 8, "id": 99477326844276736, "id_str": "99477326844276736"}